README.rst
setup.py
sphinxcontrib/__init__.py
sphinxcontrib/japanese_text_join.py
sphinxcontrib_japanese_text_join.egg-info/PKG-INFO
sphinxcontrib_japanese_text_join.egg-info/SOURCES.txt
sphinxcontrib_japanese_text_join.egg-info/dependency_links.txt
sphinxcontrib_japanese_text_join.egg-info/namespace_packages.txt
sphinxcontrib_japanese_text_join.egg-info/top_level.txt