Metadata-Version: 1.0
Name: sphinxcontrib-japanese-text-join
Version: 0.1.0
Summary: japanese-text-join
Home-page: https://github.com/draftcode/japanese-text-join
Author: Masaya SUZUKI
Author-email: draftcode@gmail.com
License: UNKNOWN
Platform: UNKNOWN
